_spx_haraka_256s.abi3.so
_spx_shake_256s.abi3.so
_spx_shake_192s.abi3.so
_spx_sha2_192f.abi3.so
_spx_haraka_192f.abi3.so
_spx_shake_256f.abi3.so
_spx_sha2_192s.abi3.so
_spx_sha2_128s.abi3.so
_spx_shake_128f.abi3.so
_spx_haraka_192s.abi3.so
_spx_sha2_256s.abi3.so
_spx_haraka_128s.abi3.so
_spx_sha2_256f.abi3.so
_spx_haraka_128f.abi3.so
_spx_sha2_128f.abi3.so
_spx_haraka_256f.abi3.so
_spx_shake_128s.abi3.so
_spx_shake_192f.abi3.so
PySPX-0.5.0.dist-info/top_level.txt
PySPX-0.5.0.dist-info/METADATA
PySPX-0.5.0.dist-info/RECORD
PySPX-0.5.0.dist-info/WHEEL
PySPX-0.5.0.dist-info/LICENSE
pyspx/haraka_128s.py
pyspx/sha2_128s.py
pyspx/build.py
pyspx/__init__.py
pyspx/sha2_192s.py
pyspx/sha2_192f.py
pyspx/haraka_256f.py
pyspx/haraka_192s.py
pyspx/shake_192f.py
pyspx/haraka_192f.py
pyspx/shake_192s.py
pyspx/haraka_256s.py
pyspx/shake_256f.py
pyspx/haraka_128f.py
pyspx/shake_128s.py
pyspx/shake_128f.py
pyspx/sha2_128f.py
pyspx/shake_256s.py
pyspx/sha2_256s.py
pyspx/sha2_256f.py
pyspx/bindings.py
