Metadata-Version: 2.1
Name: PySPX
Version: 0.5.0
Summary: Python bindings for SPHINCS+
Home-page: https://github.com/sphincs/pyspx
Author: Joost Rijneveld, Peter Schwabe, Ruben Gonzalez
Author-email: contact@sphincs.org
License: UNKNOWN
Platform: UNKNOWN
Classifier: Topic :: Security :: Cryptography
Classifier: Development Status :: 3 - Alpha
Classifier: Intended Audience :: Developers
Classifier: License :: CC0 1.0 Universal (CC0 1.0) Public Domain Dedication
Classifier: Programming Language :: Python :: 3
License-File: LICENSE
